hoellental_null/__init__.py
hoellental_null/hoellental.py
hoellental-0.0.1.dist-info/LICENSE
hoellental-0.0.1.dist-info/METADATA
hoellental-0.0.1.dist-info/WHEEL
hoellental-0.0.1.dist-info/top_level.txt
hoellental-0.0.1.dist-info/RECORD
